tprofile
