Metadata-Version: 1.0
Name: tprofile
Version: 0.0.16
Summary: a profile tool for tornado web requesthandler
Home-page: http://timd.cn/
Author: timchow
Author-email: jordan23nbastar@yeah.net
License: LGPL
Keywords: tornado profile
Platform: UNKNOWN
